<TestExample xmlns="Delight" xmlns:xsi="http://www.w3.org/2001/XMLSchema-instance" xsi:schemaLocation="Delight ../Delight.xsd" BasedOn="LayoutRoot">

  <Group> 
    <List Items="{level in @FilteredDemoLevels}" ItemSelected="OnItemSelected">
      <ListItem Click="$ Button1.Text = level.Name">
        <Group Orientation="Horizontal">
          <Label Text="$ {level.Name}" AutoSize="True" />
          <Label Text="$ Test2(40)" AutoSize="True" />
        </Group>
      </ListItem>
    </List>
    <Button Text="Test" Click="Test" />
    <Label Text="$ Test2(10)" /> 
  </Group>

</TestExample>
